{
  "profile": [
    {
      "nome": "felipe",
      "email": "felipe@alura.com",
      "id": 1
    },
    {
      "nome": "mateus",
      "email": "mateus@gmail.com",
      "id": 2
    },
    {
      "nome": "mateus",
      "email": "mateus@gmail.com",
      "id": 3
    },
    {
      "nome": "mateus",
      "email": "mateus@gmail.com",
      "id": 4
    },
    {
      "nome": "mateus",
      "email": "mateus@gmail.com",
      "id": 5
    },
    {
      "nome": "mateus",
      "email": "mateus@gmail.com",
      "id": 6
    },
    {
      "nome": "mateus",
      "email": "mateus@gmail.com",
      "id": 7
    },
    {
      "nome": "mateus",
      "email": "mateus@gmail.com",
      "id": 8
    }
  ]
}